google_injector/__init__.py
google_injector/_Injector.py
google_injector/base/__init__.py
google_injector/base/FirebaseCore.py
google_injector/base/GoogleAuth.py
google_injector/exc/__init__.py
google_injector/fire/__init__.py
google_injector/fire/Authentication.py
google_injector/fire/Config.py
google_injector/fire/Database.py
google_injector/fire/PyreResponse.py
google_injector/fire/Storage.py
google_injector/fire/Stream.py
google_injector/response/__init__.py
google_injector/utils/__init__.py
google_injector/utils/Key_Base64.py
google_injector/utils/types.py
google_injector-1.0.3.dist-info/WHEEL
google_injector-1.0.3.dist-info/METADATA
google_injector-1.0.3.dist-info/RECORD
