Metadata-Version: 2.1
Name: google-injector
Version: 1.0.3
Summary: 
Author: Antoni Oktha Fernandes
Author-email: 37358597+DesKaOne@users.noreply.github.com
Requires-Python: >=3.8,<4.0
Classifier: Programming Language :: Python :: 3
Classifier: Programming Language :: Python :: 3.8
Classifier: Programming Language :: Python :: 3.9
Classifier: Programming Language :: Python :: 3.10
Classifier: Programming Language :: Python :: 3.11
Requires-Dist: gcloud (>=0.18.3,<0.19.0)
Requires-Dist: http-injector (>=1.0.1,<2.0.0)
Requires-Dist: oauth2client (>=4.1.3,<5.0.0)
Requires-Dist: pycryptodomex (>=3.20.0,<4.0.0)
Requires-Dist: python-dotenv (>=1.0.1,<2.0.0)
Requires-Dist: python-jwt (>=4.1.0,<5.0.0)
Requires-Dist: sqlalchemy (>=2.0.29,<3.0.0)
Requires-Dist: sqlalchemy-utils (>=0.41.2,<0.42.0)
